<?xml version="1.0" encoding="utf-8"?>
<LanguageData>
  <!--The following translations were generated by https://www.deepl.com/-->
  <!-- EN: Insulation (Biomass) -->
  <InsulationBiomass.label>Izolace (Biomasa)</InsulationBiomass.label>
  <!-- EN: Grants the ability to insulate walls and doors with biomass. -->
  <InsulationBiomass.description>Poskytuje možnost izolovat stěny a dveře biomasou.</InsulationBiomass.description>
  <!-- EN: Insulation (Fibres) -->
  <InsulationFibres.label>Izolace (Vlákna)</InsulationFibres.label>
  <!-- EN: Grants the ability to insulate walls and doors with fibres. -->
  <InsulationFibres.description>Poskytuje možnost izolovat stěny a dveře pomocí vláken.</InsulationFibres.description>
  <!-- EN: Insulation (Hyper) -->
  <InsulationHyper.label>Izolace (Hyper)</InsulationHyper.label>
  <!-- EN: Grants the ability to insulate walls and doors with advanced materials. -->
  <InsulationHyper.description>Poskytuje možnost izolovat stěny a dveře pomocí pokročilých materiálů.</InsulationHyper.description>
  <!-- EN: Insulation (Polymers) -->
  <InsulationPolymers.label>Izolace (Polymery)</InsulationPolymers.label>
  <!-- EN: Grants the ability to insulate walls and doors with synthetic polymers. -->
  <InsulationPolymers.description>Poskytuje možnost izolovat stěny a dveře syntetickými polymery.</InsulationPolymers.description>
</LanguageData>
