<?xml version="1.0" encoding="utf-8"?>
<LanguageData>
  <!--The following translations were generated by https://www.deepl.com/-->
  <!-- EN: Insulation (Biomass) -->
  <InsulationBiomass.label>Izolare (Biomasă)</InsulationBiomass.label>
  <!-- EN: Grants the ability to insulate walls and doors with biomass. -->
  <InsulationBiomass.description>Acordă posibilitatea de a izola pereții și ușile cu biomasă.</InsulationBiomass.description>
  <!-- EN: Insulation (Fibres) -->
  <InsulationFibres.label>Izolație (fibre)</InsulationFibres.label>
  <!-- EN: Grants the ability to insulate walls and doors with fibres. -->
  <InsulationFibres.description>Acordă posibilitatea de a izola pereții și ușile cu fibre.</InsulationFibres.description>
  <!-- EN: Insulation (Hyper) -->
  <InsulationHyper.label>Izolare (Hyper)</InsulationHyper.label>
  <!-- EN: Grants the ability to insulate walls and doors with advanced materials. -->
  <InsulationHyper.description>Acordă capacitatea de a izola pereții și ușile cu materiale avansate.</InsulationHyper.description>
  <!-- EN: Insulation (Polymers) -->
  <InsulationPolymers.label>Izolare (polimeri)</InsulationPolymers.label>
  <!-- EN: Grants the ability to insulate walls and doors with synthetic polymers. -->
  <InsulationPolymers.description>Acordă capacitatea de a izola pereții și ușile cu polimeri sintetici.</InsulationPolymers.description>
</LanguageData>
