<?xml version="1.0" encoding="utf-8"?>
<LanguageData>
  <!--The following translations were generated by https://www.deepl.com/-->
  <!-- EN: Make Insulation slabs (biomass) -->
  <Make_INSSlab_Biomass.label>Fazer placas de isolamento (biomassa)</Make_INSSlab_Biomass.label>
  <!-- EN: Make 5 Insulation slabs (biomass). -->
  <Make_INSSlab_Biomass.description>Faça 5 placas de isolamento (biomassa).</Make_INSSlab_Biomass.description>
  <!-- EN: Making insulation slabs. -->
  <Make_INSSlab_Biomass.jobString>Fazendo placas de isolamento.</Make_INSSlab_Biomass.jobString>
  <!-- EN: Make Insulation slabs (biomass) in bulk -->
  <MakeBulk_INSSlab_Biomass.label>Faça placas de isolamento (biomassa) em massa</MakeBulk_INSSlab_Biomass.label>
  <!-- EN: Make 25 Insulation slabs (biomass). -->
  <MakeBulk_INSSlab_Biomass.description>Faça 25 placas de isolamento (biomassa).</MakeBulk_INSSlab_Biomass.description>
  <MakeBulk_INSSlab_Biomass.jobString>Fazendo placas de isolamento.</MakeBulk_INSSlab_Biomass.jobString>
</LanguageData>
